Metadata-Version: 2.1
Name: odoo12-addon-graphql-base
Version: 12.0.2.0.1
Summary: Base GraphQL/GraphiQL controller
Home-page: https://github.com/OCA/rest-framework
Author: ACSONE SA/NV,Odoo Community Association (OCA)
Author-email: support@odoo-community.org
License: LGPL-3
Platform: UNKNOWN
Classifier: Programming Language :: Python
Classifier: Framework :: Odoo
Classifier: Framework :: Odoo :: 12.0
Classifier: License :: OSI Approved :: GNU Lesser General Public License v3 (LGPLv3)
Classifier: Development Status :: 4 - Beta
Requires-Python: >=3.5
Requires-Dist: graphene (<3)
Requires-Dist: graphql-server-core
Requires-Dist: odoo (<12.1dev,>=12.0a)
